pdm_shell.py
pdm_shell-1.1.0.dist-info/entry_points.txt
pdm_shell-1.1.0.dist-info/WHEEL
pdm_shell-1.1.0.dist-info/METADATA
pdm_shell-1.1.0.dist-info/licenses/LICENSE
pdm_shell-1.1.0.dist-info/RECORD
