Metadata-Version: 2.1
Name: pdm-shell
Version: 1.1.0
Summary: Use `pdm shell` set PATH and PYTHONPATH in the current shell
License: Apache2.0
Author-email: abersheeran <me@abersheeran.com>
Requires-Python: >=3.7
Requires-Dist: pdm>=1.8
Project-URL: homepage, https://github.com/abersheeran/pdm-shell
